mpaia/__init__.py
mpaia/assistant.py
mpaia/bot.py
mpaia/jobs.py
mpaia/telegram_bot.py
mpaia-0.1.1.dist-info/METADATA
mpaia-0.1.1.dist-info/WHEEL
mpaia-0.1.1.dist-info/top_level.txt
mpaia-0.1.1.dist-info/RECORD
