Metadata-Version: 2.1
Name: mpaia
Version: 0.1.1
Summary: My Personal AI Assistant
Author-email: Tomer Gabay <tomergabay001@gmail.com>
License: MIT
Project-URL: Homepage, https://github.com/sTomerG/mpaia
Project-URL: Bug Tracker, https://github.com/sTomerG/mpaia/issues
Classifier: Programming Language :: Python :: 3
Classifier: License :: OSI Approved :: MIT License
Classifier: Operating System :: OS Independent
Requires-Python: >=3.11
Requires-Dist: python-telegram-bot>=20.8
Requires-Dist: python-dotenv>=1.0.1
Requires-Dist: openai>=1.45.0
Requires-Dist: langchain>=0.3.0
Requires-Dist: langchain-openai>=0.2.0
Requires-Dist: langchain-community>=0.3.0
Requires-Dist: loguru>=0.7.2
Requires-Dist: APScheduler>=3.10.4
Provides-Extra: test
Requires-Dist: pre-commit==3.*; extra == "test"
